ripa/__init__.py
ripa/cli.py
ripa/ripa.py
ripa-0.2.0.dist-info/DESCRIPTION.rst
ripa-0.2.0.dist-info/METADATA
ripa-0.2.0.dist-info/RECORD
ripa-0.2.0.dist-info/WHEEL
ripa-0.2.0.dist-info/entry_points.txt
ripa-0.2.0.dist-info/metadata.json
ripa-0.2.0.dist-info/top_level.txt
