Metadata-Version: 2.0
Name: ripa
Version: 0.2.0
Summary: This tool helps you handle requirements.txt installations (e.g. in CI) where uses Anaconda for some packages but also wants pip packages.
Home-page: https://github.com/tunnell/ripa
Author: Christopher Tunnell
Author-email: christopher.douglas.tunnell+ripa@gmail.com
License: GNU General Public License v3
Keywords: ripa
Platform: UNKNOWN
Classifier: Development Status :: 3 - Alpha
Classifier: Intended Audience :: Developers
Classifier: License :: OSI Approved :: GNU General Public License v3 (GPLv3)
Classifier: Natural Language :: English
Classifier: Programming Language :: Python :: 3
Classifier: Programming Language :: Python :: 3.4
Classifier: Programming Language :: Python :: 3.5
Classifier: Programming Language :: Python :: 3.6
Requires-Dist: Click (>=6.0)
Requires-Dist: requirements-parser
